mock_di_api
