Metadata-Version: 2.1
Name: mock-di-api
Version: 0.0.5
Summary: Mocking SAP Data Intelligence api for local testing
Home-page: UNKNOWN
Author: Thorsten Hapke
Author-email: thorsten.hapke@sap.com
License: UNKNOWN
Keywords: SAP Data Intelligence,local development,mocking api
Platform: UNKNOWN
Classifier: Programming Language :: Python :: 3.5
Classifier: Programming Language :: Python :: 3.6
Classifier: Programming Language :: Python :: 3.7
Classifier: Programming Language :: Python :: 3.8
Classifier: License :: OSI Approved :: MIT License
Classifier: Operating System :: OS Independent
